datalad_catalog/__init__.py
datalad_catalog/_version.py
datalad_catalog/add.py
datalad_catalog/catalog.py
datalad_catalog/conftest.py
datalad_catalog/constants.py
datalad_catalog/constraints.py
datalad_catalog/create.py
datalad_catalog/get.py
datalad_catalog/meta_item.py
datalad_catalog/node.py
datalad_catalog/remove.py
datalad_catalog/schema_utils.py
datalad_catalog/serve.py
datalad_catalog/set.py
datalad_catalog/translate.py
datalad_catalog/utils.py
datalad_catalog/validate.py
datalad_catalog/webcatalog.py
datalad_catalog/workflow.py
datalad_catalog/catalog/README.md
datalad_catalog/catalog/config.json
datalad_catalog/catalog/display_schema.html
datalad_catalog/catalog/index.html
datalad_catalog/catalog/metadata-entry.html
datalad_catalog/catalog/artwork/404.svg
datalad_catalog/catalog/artwork/catalog_logo.svg
datalad_catalog/catalog/artwork/datalad_catalog_logo_1_dark.svg
datalad_catalog/catalog/artwork/datalad_catalog_logo_1_light.svg
datalad_catalog/catalog/artwork/datalad_logo_wide.svg
datalad_catalog/catalog/artwork/ginfavicon.png
datalad_catalog/catalog/assets/app.js
datalad_catalog/catalog/assets/app_component_about.js
datalad_catalog/catalog/assets/app_component_contexttab.js
datalad_catalog/catalog/assets/app_component_dataset.js
datalad_catalog/catalog/assets/app_component_item.js
datalad_catalog/catalog/assets/app_component_notfound.js
datalad_catalog/catalog/assets/app_globals.js
datalad_catalog/catalog/assets/app_router.js
datalad_catalog/catalog/assets/bootstrap-vue.2.21.2.min.css
datalad_catalog/catalog/assets/bootstrap-vue.2.21.2.min.js
datalad_catalog/catalog/assets/bootstrap.5.1.3.min.css
datalad_catalog/catalog/assets/brands.min.css
datalad_catalog/catalog/assets/display_schema.js
datalad_catalog/catalog/assets/fa-brands-400.woff2
datalad_catalog/catalog/assets/fa-regular-400.woff2
datalad_catalog/catalog/assets/fa-solid-900.woff2
datalad_catalog/catalog/assets/fontawesome.min.css
datalad_catalog/catalog/assets/jsonschema_authors.json
datalad_catalog-1.1.1.dist-info/LICENSE
datalad_catalog-1.1.1.dist-info/METADATA
datalad_catalog-1.1.1.dist-info/WHEEL
datalad_catalog-1.1.1.dist-info/entry_points.txt
datalad_catalog-1.1.1.dist-info/top_level.txt
datalad_catalog-1.1.1.dist-info/RECORD
