Metadata-Version: 2.1
Name: datalad_catalog
Version: 1.1.1
Summary: DataLad Catalog
Home-page: https://github.com/datalad/datalad-catalog
Author: DataLad Developers
Author-email: team@datalad.org
License: MIT
Classifier: Programming Language :: Python
Classifier: License :: OSI Approved :: BSD License
Classifier: Programming Language :: Python :: 3
Requires-Python: >=3.7
License-File: LICENSE
Requires-Dist: datalad >=0.19
Requires-Dist: datalad-metalad >=0.4.6
Requires-Dist: datalad-next >=1.0.0b3
Requires-Dist: jsonschema
Requires-Dist: pyyaml
Requires-Dist: jq ; platform_system != "Windows"
Provides-Extra: devel
Requires-Dist: coverage ; extra == 'devel'
Requires-Dist: pytest ; extra == 'devel'
